phylim/__init__.py
phylim/_version.py
phylim/apps.py
phylim/check_boundary.py
phylim/classify_matrix.py
phylim/eval_identifiability.py
phylim-2025.8.27.dist-info/entry_points.txt
phylim-2025.8.27.dist-info/licenses/LICENSE
phylim-2025.8.27.dist-info/WHEEL
phylim-2025.8.27.dist-info/METADATA
phylim-2025.8.27.dist-info/RECORD
