Metadata-Version: 2.4
Name: phylim
Version: 2025.8.27
Summary: A library for checking the limits of phylogenetic tree estimation.
Keywords: biology,genomics,statistics,phylogeny,evolution,bioinformatics
Author-email: Yapeng Lang <u7181074@anu.edu.au>, Gavin Huttley <Gavin.Huttley@anu.edu.au>
Requires-Python: >=3.11,<3.14
Classifier: Development Status :: 2 - Pre-Alpha
Classifier: Intended Audience :: Science/Research
Classifier: License :: OSI Approved :: BSD License
Classifier: Topic :: Scientific/Engineering :: Bio-Informatics
Classifier: Topic :: Software Development :: Libraries :: Python Modules
Classifier: Operating System :: OS Independent
Classifier: Programming Language :: Python :: 3.11
Classifier: Programming Language :: Python :: 3.12
Classifier: Programming Language :: Python :: 3.13
License-File: LICENSE
Requires-Dist: numpy
Requires-Dist: cogent3>=2025.7.10a3
Requires-Dist: black ; extra == "dev"
Requires-Dist: click ; extra == "dev"
Requires-Dist: docformatter ; extra == "dev"
Requires-Dist: flit ; extra == "dev"
Requires-Dist: isort ; extra == "dev"
Requires-Dist: pytest ; extra == "dev"
Requires-Dist: pytest-cov ; extra == "dev"
Requires-Dist: pytest-xdist ; extra == "dev"
Requires-Dist: nox ; extra == "dev"
Requires-Dist: pytest ; extra == "test"
Requires-Dist: pytest-cov ; extra == "test"
Requires-Dist: pytest-xdist ; extra == "test"
Requires-Dist: nox ; extra == "test"
Requires-Dist: piqtree>=0.6.0 ; extra == "test"
Project-URL: Bug Tracker, https://github.com/HuttleyLab/PhyLim/issues
Project-URL: Source Code, https://github.com/HuttleyLab/PhyLim
Provides-Extra: dev
Provides-Extra: test
